deepali/__init__.py
deepali-0.1.dist-info/METADATA
deepali-0.1.dist-info/WHEEL
deepali-0.1.dist-info/top_level.txt
deepali-0.1.dist-info/RECORD
