Metadata-Version: 2.1
Name: deepali
Version: 0.1
Summary: sum of two number
Home-page: UNKNOWN
Author: deepali
Author-email: deepali.sharma@sganalytics.com
License: MIT
Platform: UNKNOWN
